traceai_llamaindex/__init__.py
traceai_llamaindex/_callback.py
traceai_llamaindex/_handler.py
traceai_llamaindex/package.py
traceai_llamaindex/py.typed
traceai_llamaindex/version.py
traceai_llamaindex-0.1.8.dist-info/METADATA
traceai_llamaindex-0.1.8.dist-info/WHEEL
traceai_llamaindex-0.1.8.dist-info/RECORD
