Metadata-Version: 2.3
Name: traceAI-llamaindex
Version: 0.1.8
Summary: OpenTelemetry instrumentation for Llama Index
Author: Future AGI
Author-email: no-reply@futureagi.com
Requires-Python: >3.9,<3.14
Classifier: Programming Language :: Python :: 3
Classifier: Programming Language :: Python :: 3.10
Classifier: Programming Language :: Python :: 3.11
Classifier: Programming Language :: Python :: 3.12
Classifier: Programming Language :: Python :: 3.13
Requires-Dist: fi-instrumentation-otel (>=0.1.11)
Requires-Dist: llama-index-core (>=0.10.43)
